{
  "generatedAt": "2026-06-15T00:13:03.243Z",
  "totalCount": 943,
  "byRole": {
    "CEO": 50,
    "Staff": 0,
    "Bot": 893
  },
  "recent10": [
    {
      "at": "2026-06-15T00:02",
      "by": "🤖 scan-bot",
      "action": "[scan-bot] pages-status 3-Layer 자동 갱신 (21페이지, 평균 70점) [변경사유: HTML 변경 → 완성도 재측정]"
    },
    {
      "at": "2026-06-14T23:53",
      "by": "🤖 scan-bot",
      "action": "[scan-bot] chat-log index 자동 갱신 [변경사유: chat-log 파일 또는 tasks.json 변경 → byCommit/b"
    },
    {
      "at": "2026-06-14T23:40",
      "by": "🤖 health-bot",
      "action": "[health-bot] _health.json 갱신 (overall=yellow)"
    },
    {
      "at": "2026-06-14T22:56",
      "by": "🤖 activity-bot",
      "action": "[activity-bot] activity-feed 3-Layer 자동 갱신 (총 943건)"
    },
    {
      "at": "2026-06-14T22:54",
      "by": "🤖 scan-bot",
      "action": "[scan-bot] pages-status 3-Layer 자동 갱신 (21페이지, 평균 70점) [변경사유: HTML 변경 → 완성도 재측정]"
    },
    {
      "at": "2026-06-14T22:41",
      "by": "🤖 scan-bot",
      "action": "[scan-bot] chat-log index 자동 갱신 [변경사유: chat-log 파일 또는 tasks.json 변경 → byCommit/b"
    },
    {
      "at": "2026-06-14T22:17",
      "by": "🤖 health-bot",
      "action": "[health-bot] _health.json 갱신 (overall=yellow)"
    },
    {
      "at": "2026-06-14T21:49",
      "by": "🤖 activity-bot",
      "action": "[activity-bot] activity-feed 3-Layer 자동 갱신 (총 943건)"
    },
    {
      "at": "2026-06-14T21:46",
      "by": "🤖 scan-bot",
      "action": "[scan-bot] pages-status 3-Layer 자동 갱신 (21페이지, 평균 70점) [변경사유: HTML 변경 → 완성도 재측정]"
    },
    {
      "at": "2026-06-14T21:22",
      "by": "🤖 scan-bot",
      "action": "[scan-bot] chat-log index 자동 갱신 [변경사유: chat-log 파일 또는 tasks.json 변경 → byCommit/b"
    }
  ]
}