{
  "generatedAt": "2026-05-18T05:09:01.579Z",
  "totalCount": 714,
  "byRole": {
    "CEO": 82,
    "Staff": 0,
    "Bot": 632
  },
  "recent10": [
    {
      "at": "2026-05-18T14:08",
      "by": "👤 이지형 (CEO)",
      "action": "docs(BL-MGR-DASHBOARD-V1): D-040 매니저 대시보드 V1 출시 박제 [step:done:3] [변경사유:decision-"
    },
    {
      "at": "2026-05-18T14:08",
      "by": "👤 이지형 (CEO)",
      "action": "feat(BL-MGR-DASHBOARD-V1): V1 출시 done + stats 재계산 [step:done:3] [변경사유:v1-release"
    },
    {
      "at": "2026-05-18T05:07",
      "by": "🤖 scan-bot",
      "action": "[scan-bot] chat-log index 자동 갱신 [변경사유: chat-log 파일 또는 tasks.json 변경 → byCommit/b"
    },
    {
      "at": "2026-05-18T05:07",
      "by": "🤖 auto-detect-bot",
      "action": "[auto-detect-bot] commit message → 작업 status 자동 갱신"
    },
    {
      "at": "2026-05-18T05:07",
      "by": "🤖 activity-bot",
      "action": "[activity-bot] activity-feed 3-Layer 자동 갱신 (총 714건)"
    },
    {
      "at": "2026-05-18T14:07",
      "by": "👤 이지형 (CEO)",
      "action": "feat(BL-MGR-DASHBOARD-V1): stage 4 라이브 검증 chat-log 박제 [step:done:1] [변경사유:stage4"
    },
    {
      "at": "2026-05-18T05:01",
      "by": "🤖 activity-bot",
      "action": "[activity-bot] activity-feed 3-Layer 자동 갱신 (총 713건)"
    },
    {
      "at": "2026-05-18T05:01",
      "by": "🤖 health-bot",
      "action": "[health-bot] _health.json 갱신 (overall=red)"
    },
    {
      "at": "2026-05-18T05:01",
      "by": "🤖 auto-detect-bot",
      "action": "[auto-detect-bot] commit message → 작업 status 자동 갱신"
    },
    {
      "at": "2026-05-18T05:01",
      "by": "🤖 scan-bot",
      "action": "[scan-bot] chat-log index 자동 갱신 [변경사유: chat-log 파일 또는 tasks.json 변경 → byCommit/b"
    }
  ]
}