{
  "generatedAt": "2026-05-14T16:20:09.616Z",
  "totalAvgScore": 75,
  "pageCount": 19,
  "counts": {
    "🟢 완성": 0,
    "🔵 본격": 13,
    "🟡 부분": 5,
    "🟠 골격": 0,
    "🔴 미작성": 0
  },
  "criticalPages": [],
  "partialPages": [
    {
      "path": "/hotel-info.html",
      "score": 61,
      "weakest": "content"
    },
    {
      "path": "/signup.html",
      "score": 65,
      "weakest": "function"
    },
    {
      "path": "/reset-password.html",
      "score": 68,
      "weakest": "function"
    },
    {
      "path": "/admin-service-ops.html",
      "score": 68,
      "weakest": "function"
    },
    {
      "path": "/verify-email.html",
      "score": 69,
      "weakest": "function"
    }
  ],
  "sidebarScores": [
    {
      "key": "system-status",
      "score": 78
    },
    {
      "key": "task-management",
      "score": 83
    },
    {
      "key": "business-docs",
      "score": 82
    },
    {
      "key": "page-gallery",
      "score": 78
    },
    {
      "key": "service-operations",
      "score": 68
    }
  ]
}